aio_scheduler/__init__.py
aio_scheduler/adapter.py
aio_scheduler/cli.py
aio_scheduler/job.py
aio_scheduler/test.py
aio_scheduler/utils.py
aio_scheduler-0.1.0.dist-info/AUTHORS.rst
aio_scheduler-0.1.0.dist-info/LICENSE
aio_scheduler-0.1.0.dist-info/METADATA
aio_scheduler-0.1.0.dist-info/WHEEL
aio_scheduler-0.1.0.dist-info/entry_points.txt
aio_scheduler-0.1.0.dist-info/top_level.txt
aio_scheduler-0.1.0.dist-info/RECORD
