Metadata-Version: 2.1
Name: aio-scheduler
Version: 0.1.0
Summary: UNKNOWN
Home-page: https://github.com/louis-she/aio_scheduler
Author: Chenglu She
Author-email: chenglu.she@gmail.com
License: MIT license
Keywords: asyncio,redis scheduler
Platform: UNKNOWN
Classifier: Development Status :: 2 - Pre-Alpha
Classifier: Intended Audience :: Developers
Classifier: License :: OSI Approved :: MIT License
Classifier: Natural Language :: English
Classifier: Programming Language :: Python :: 3
Classifier: Programming Language :: Python :: 3.5
Classifier: Programming Language :: Python :: 3.6
Classifier: Programming Language :: Python :: 3.7
Classifier: Programming Language :: Python :: 3.8
Requires-Python: >=3.5
Requires-Dist: Click (>=7.0)
Requires-Dist: aioredis
